fortaleza_ays/__init__.py
fortaleza_ays/code.py
fortaleza_ays/code2.py
fortaleza_ays-0.0.1.dist-info/METADATA
fortaleza_ays-0.0.1.dist-info/WHEEL
fortaleza_ays-0.0.1.dist-info/top_level.txt
fortaleza_ays-0.0.1.dist-info/RECORD
