Metadata-Version: 2.1
Name: fortaleza-ays
Version: 0.0.1
Summary: For learning purpose and testing
Home-page: UNKNOWN
Author: ayush
License: UNKNOWN
Platform: UNKNOWN
Classifier: Programming Language :: Python :: 3
Classifier: License :: OSI Approved :: MIT License
Classifier: Operating System :: OS Independent
Requires-Python: >3.5
